{
    "id": "1967\u201368_MJHL_season",
    "text": "On March 14 , 1968 , at home in St. James , the St. James Canadians corralled the Manitoba Junior Hockey League championship , and on March 26 , in Selkirk , the Canadians captured the Turnbull Cup defeating the Central Manitoba Junior Hockey League champions Selkirk Steelers . ",
    "lines": "0\tOn March 14 , 1968 , at home in St. James , the St. James Canadians corralled the Manitoba Junior Hockey League championship , and on March 26 , in Selkirk , the Canadians captured the Turnbull Cup defeating the Central Manitoba Junior Hockey League champions Selkirk Steelers .\tSt. James\tSt. James, Winnipeg, Manitoba, Canada\tManitoba Junior Hockey League\tManitoba Junior Hockey League\tSelkirk\tSelkirk, Manitoba\tCentral Manitoba Junior Hockey League\tCentral Manitoba Junior Hockey League\tSelkirk Steelers\tSelkirk Steelers\n1\t"
}
{
    "id": "13th_parallel_north",
    "text": "The 13th parallel north is a circle of latitude that is 13 degrees north of the Earth 's equatorial plane . It crosses Africa , Asia , the Indian Ocean , the Pacific Ocean , Central America , the Caribbean and the Atlantic Ocean .   At this latitude the sun is visible for 12 hours , 53 minutes during the summer solstice and 11 hours , 22 minutes during the winter solstice . ",
    "lines": "0\tThe 13th parallel north is a circle of latitude that is 13 degrees north of the Earth 's equatorial plane .\tcircle of latitude\tcircle of latitude\tdegrees\tdegree (angle)\tnorth\ttrue north\tequatorial plane\tequator\n1\tIt crosses Africa , Asia , the Indian Ocean , the Pacific Ocean , Central America , the Caribbean and the Atlantic Ocean .\tAfrica\tAfrica\tAsia\tAsia\tIndian Ocean\tIndian Ocean\tPacific Ocean\tPacific Ocean\tCentral America\tCentral America\tCaribbean\tCaribbean\tAtlantic Ocean\tAtlantic Ocean\n2\t\n3\t\n4\tAt this latitude the sun is visible for 12 hours , 53 minutes during the summer solstice and 11 hours , 22 minutes during the winter solstice .\tsun\tsun\tsummer solstice\tsummer solstice\twinter solstice\twinter solstice\n5\t"
}

{
    'The': [(' The',
        0)
    ], 
    'The_-LRB-Post-RRB-_Mistress': [(' The',
        0)
    ], 
    'The_-LRB-International-RRB-_Noise_Conspiracy': [(' The',
        0)
    ], 
    'The_-LRB-Almost-RRB-_Accidental_Adventures_of_Bell_and_Todd': [(' The',
        0)
    ], 
    'The_-LRB-M-RRB-orons': [(' The',
        0)
    ], 
    'The_-LRB-Cyrillic-RRB-': [(' The',
        0)
    ], 
    'The_-LRB-206-RRB-': [(' The',
        0)
    ], 
    'The_-LRB-Original-RRB-_Church_of_God': [(' The',
        0)
    ], 
    'THE': [(' The',
        0)
    ], 
    'The_-LRB-disambiguation-RRB-': [(' The',
        0)
    ], 
    '2016': [(' 2016',
        1)
    ], 
    '2016_-LRB-disambiguation-RRB-': [(' 2016',
        1)
    ], 
    '2016_-LRB-2010_film-RRB-': [(' 2016',
        1)
    ], 
    'Summer_-LRB-Shy_Child_song-RRB-': [(' Summer',
        2)
    ], 
    'Summer_-LRB-George_Winston_album-RRB-': [(' Summer',
        2)
    ], 
    'Summer_-LRB-Cassadee_Pope_song-RRB-': [(' Summer',
        2)
    ], 
    'Summer_-LRB-given_name-RRB-': [(' Summer',
        2)
    ], 
    'Summer_-LRB-Mogwai_composition-RRB-': [(' Summer',
        2)
    ], 
    'Summer_-LRB-visual_novel-RRB-': [(' Summer',
        2)
    ], 
    'Summer': [(' Summer',
        2)
    ], 
    'Summer_-LRB-1930_film-RRB-': [(' Summer',
        2)
    ], 
    'Summer_-LRB-2011_film-RRB-': [(' Summer',
        2)
    ], 
    'Summer_-LRB-Summer_Watson_album-RRB-': [(' Summer',
        2)
    ], 
    'Summer_-LRB-disambiguation-RRB-': [(' Summer',
        2)
    ], 
    'Summer_-LRB-Tohoshinki_EP-RRB-': [(' Summer',
        2)
    ], 
    'Summer_-LRB-Jon_Foreman_EP-RRB-': [(' Summer',
        2)
    ], 
    'Summer_-LRB-Calvin_Harris_song-RRB-': [(' Summer',
        2)
    ], 
    'Summer_-LRB-Cassadee_Pope_EP-RRB-': [(' Summer',
        2)
    ], 
    'Summer_-LRB-Subtle_EP-RRB-': [(' Summer',
        2)
    ], 
    'Summer_-LRB-War_song-RRB-': [(' Summer',
        2)
    ], 
    'Summer_-LRB-2008_film-RRB-': [(' Summer',
        2)
    ], 
    'Summer_-LRB-Harisu_album-RRB-': [(' Summer',
        2)
    ], 
    'Summer_-LRB-surname-RRB-': [(' Summer',
        2)
    ], 
    'Summer_-LRB-novel-RRB-': [(' Summer',
        2)
    ], 
    '2016_Summer_Olympics': [(' 2016 Summer Olympics',
        1)
    ], 
    'Took': [(' took',
        4)
    ], 
    'Took_-LRB-disambiguation-RRB-': [(' took',
        4)
    ], 
    'Took_-LRB-The_Wire-RRB-': [(' took',
        4)
    ], 
    'Place_-LRB-surname-RRB-': [(' place',
        5)
    ], 
    'Place': [(' place',
        5)
    ], 
    'Place_-LRB-United_States_Census_Bureau-RRB-': [(' place',
        5)
    ], 
    'Place_-LRB-Reddit-RRB-': [(' place',
        5)
    ], 
    'IN': [(' in',
        6)
    ], 
    'In_-LRB-Korean_name-RRB-': [(' in',
        6)
    ], 
    'In_-LRB-The_Outsiders_album-RRB-': [(' in',
        6)
    ], 
    'August_-LRB-Woodward_novel-RRB-': [(' August',
        7)
    ], 
    'August_-LRB-band-RRB-': [(' August',
        7)
    ], 
    'August_-LRB-company-RRB-': [(' August',
        7)
    ], 
    'August': [(' August',
        7)
    ], 
    'August_-LRB-disambiguation-RRB-': [(' August',
        7)
    ], 
    'August_-LRB-2011_film-RRB-': [(' August',
        7)
    ], 
    'August_-LRB-Eric_Clapton_album-RRB-': [(' August',
        7)
    ], 
    'August_-LRB-1996_film-RRB-': [(' August',
        7)
    ], 
    'August_-LRB-name-RRB-': [(' August',
        7)
    ], 
    'August_-LRB-Fringe-RRB-': [(' August',
        7)
    ], 
    'August_-LRB-Elevator_album-RRB-': [(' August',
        7)
    ], 
    'August_-LRB-2008_film-RRB-': [(' August',
        7)
    ], 
    'August_-LRB-Rossner_novel-RRB-': [(' August',
        7)
    ], 
    'In_August': [(' in August',
        6)
    ]
}

{
    "id": 91198,
    "scores": [
        [
            0.060249265283346176,
            0.8224031925201416,
            0.11734747886657715
        ],
        [
            0.008583440445363522,
            0.9715169668197632,
            0.01989961974322796
        ],
        [
            0.02422068826854229,
            0.9197214245796204,
            0.05605798587203026
        ],
        [
            0.03654136136174202,
            0.858111560344696,
            0.10534703731536865
        ],
        [
            0.00082398735685274,
            0.9982288479804993,
            0.0009471842786297202
        ]
    ],
    "claim": "Colin Kaepernick became a starting quarterback during the 49ers 63rd season in the National Football League.",
    "predicted_sentences": [
        "# Colin Kaepernick # He remained the team 's starting quarterback for the rest of the season and went on to lead the 49ers to their first Super Bowl appearance since 1994 , losing to the Baltimore Ravens .",
        "# Colin Kaepernick # Colin Rand Kaepernick -LRB- -LSB- ` k\u00e6p\u0259rn\u026ak -RSB- ; born November 3 , 1987 -RRB- is an American football quarterback who is currently a free agent .",
        "# Colin Kaepernick # Kaepernick began his professional career as a backup to Alex Smith , but became the 49ers ' starter in the middle of the 2012 season after Smith suffered a concussion .",
        "# Colin Kaepernick # During the 2013 season , his first full season as a starter , Kaepernick helped the 49ers reach the NFC Championship , losing to the Seattle Seahawks .",
        "# National Football League # Following the conclusion of the regular season , six teams from each conference -LRB- four division winners and two wild card teams -RRB- advance to the playoffs , a single-elimination tournament culminating in the Super Bowl , which is usually held in the first Sunday in February , and is played between the champions of the NFC and AFC ."
    ],
    "label": "NOT ENOUGH INFO",
    "predicted_labels": [
        [
            [
                "SUPPORTS",
                "NOT ENOUGH INFO",
                "REFUTES"
            ],
            [
                "SUPPORTS",
                "NOT ENOUGH INFO",
                "REFUTES"
            ],
            [
                "SUPPORTS",
                "NOT ENOUGH INFO",
                "REFUTES"
            ],
            [
                "SUPPORTS",
                "NOT ENOUGH INFO",
                "REFUTES"
            ],
            [
                "SUPPORTS",
                "NOT ENOUGH INFO",
                "REFUTES"
            ]
        ]
    ],
    "ev_scores": [
        [
            "Colin_Kaepernick",
            6,
            0.7826285362243652
        ],
        [
            "Colin_Kaepernick",
            0,
            0.6510575413703918
        ],
        [
            "Colin_Kaepernick",
            5,
            0.6377535462379456
        ],
        [
            "Colin_Kaepernick",
            7,
            0.5362232327461243
        ],
        [
            "National_Football_League",
            3,
            0.47192618250846863
        ]
    ]
}